odoo/addons/filter_multi_user/README.rst
odoo/addons/filter_multi_user/__init__.py
odoo/addons/filter_multi_user/__manifest__.py
odoo/addons/filter_multi_user/i18n/es.po
odoo/addons/filter_multi_user/i18n/filter_multi_user.pot
odoo/addons/filter_multi_user/i18n/it.po
odoo/addons/filter_multi_user/i18n/tr.po
odoo/addons/filter_multi_user/models/__init__.py
odoo/addons/filter_multi_user/models/ir_filters.py
odoo/addons/filter_multi_user/readme/CONFIGURE.md
odoo/addons/filter_multi_user/readme/CONTRIBUTORS.md
odoo/addons/filter_multi_user/readme/DESCRIPTION.md
odoo/addons/filter_multi_user/security/ir_filters_security.xml
odoo/addons/filter_multi_user/static/description/icon.png
odoo/addons/filter_multi_user/static/description/index.html
odoo/addons/filter_multi_user/tests/__init__.py
odoo/addons/filter_multi_user/tests/test_filter_multi_user.py
odoo/addons/filter_multi_user/views/ir_filters_view.xml
odoo_addon_filter_multi_user-18.0.1.0.0.3.dist-info/METADATA
odoo_addon_filter_multi_user-18.0.1.0.0.3.dist-info/WHEEL
odoo_addon_filter_multi_user-18.0.1.0.0.3.dist-info/top_level.txt
odoo_addon_filter_multi_user-18.0.1.0.0.3.dist-info/RECORD
